pydamodb/__init__.py
pydamodb/conditions.py
pydamodb/exceptions.py
pydamodb/expressions.py
pydamodb/fields.py
pydamodb/keys.py
pydamodb/models.py
pydamodb/mypy.py
pydamodb-0.1.1.dist-info/licenses/LICENSE
pydamodb-0.1.1.dist-info/WHEEL
pydamodb-0.1.1.dist-info/METADATA
pydamodb-0.1.1.dist-info/RECORD
