Metadata-Version: 2.4
Name: pydamodb
Version: 0.1.1
Summary: A Pydantic-based lightweight ODM for Amazon DynamoDB.
License-Expression: MIT
License-File: LICENSE
Classifier: Development Status :: 4 - Beta
Classifier: Intended Audience :: Developers
Classifier: License :: OSI Approved :: MIT License
Classifier: Programming Language :: Python
Classifier: Programming Language :: Python :: Implementation :: CPython
Classifier: Programming Language :: Python :: Implementation :: PyPy
Classifier: Programming Language :: Python :: 3
Classifier: Programming Language :: Python :: 3 :: Only
Classifier: Programming Language :: Python :: 3.10
Classifier: Programming Language :: Python :: 3.11
Classifier: Programming Language :: Python :: 3.12
Classifier: Programming Language :: Python :: 3.13
Classifier: Programming Language :: Python :: 3.14
Classifier: Operating System :: OS Independent
Classifier: Topic :: Software Development :: Libraries :: Python Modules
Requires-Dist: pydantic>=2.0.0,<3
Requires-Dist: boto3>=1.20.0,<2
Requires-Dist: typing-extensions>=4.6.0
Requires-Python: >=3.10, <3.15
Project-URL: Homepage, https://github.com/adriantomas/pydamodb
Project-URL: Issues, https://github.com/adriantomas/pydamodb/issues
Project-URL: Repository, https://github.com/adriantomas/pydamodb
